{
  "originUrl": "https://us.demo.amelia.com/Amelia/",
  "ameliaUrl": "https://us.demo.amelia.com/Amelia/ui/lgdemo/chat",
  "chatUrl": "https://us.demo.amelia.com/Amelia/ui/lgdemo/chat",
  "parentUrl": "https://www.td.com/us/en/investing/",
  "actions": {
    "nav_real-estate-financing": {
      "url": "https://www.td.com/us/en/investing/wealth-real-estate-financing"
    },
    "nav_local-calendar": {
      "url": "https://www.td.com/us/en/personal-banking/book-appointment#/appointment-choose-date-time"
    },
    "nav_online-mobile-banking-faq": {
      "url": "https://www.td.com/us/en/personal-banking/search?query=How%20do%20I%20enroll%20in%20Online%20or%20Mobile%20Banking&source=1"
    },  
    "nav_local-branch": {
      "url": "https://locations.td.com/us/12200-w-colonial-dr-winter-garden"
    }
  }
}
